{"chunk_definitions":[{"row":50,"row_count":1,"visible":true,"expansion_state":0,"options":{"engine":"r","warning":false,"label":"unnamed-chunk-94"},"document_id":"3D37876B","chunk_id":"c39afd17g8rzr","chunk_label":"unnamed-chunk-1"},{"row":111,"row_count":1,"visible":true,"expansion_state":0,"options":{"engine":"r","label":"unnamed-chunk-95"},"document_id":"3D37876B","chunk_id":"cxt8a0h2hkahb","chunk_label":"tbl-LABEL"},{"row":117,"row_count":1,"visible":true,"expansion_state":0,"options":{"engine":"r","label":"unnamed-chunk-65"},"document_id":"3D37876B","chunk_id":"c6g9o9adrdosy","chunk_label":"unnamed-chunk-2"},{"row":121,"row_count":1,"visible":true,"expansion_state":0,"options":{"engine":"r","label":"unnamed-chunk-66"},"document_id":"3D37876B","chunk_id":"cpw3egt0tcihn","chunk_label":"unnamed-chunk-3"},{"row":164,"row_count":1,"visible":true,"expansion_state":1,"options":{"tbl-cap":"CAPTION","engine":"r","label":"unnamed-chunk-96"},"document_id":"3D37876B","chunk_id":"c4yyrd2vxqh2f","chunk_label":"tbl-LABEL2"},{"row":170,"row_count":1,"visible":true,"expansion_state":0,"options":{"engine":"r","label":"unnamed-chunk-69"},"document_id":"3D37876B","chunk_id":"chzkty5z9ru43","chunk_label":"unnamed-chunk-4"},{"row":174,"row_count":1,"visible":true,"expansion_state":0,"options":{"engine":"r","label":"unnamed-chunk-70"},"document_id":"3D37876B","chunk_id":"cgwu3slj4ekwg","chunk_label":"unnamed-chunk-5"},{"row":189,"row_count":1,"visible":true,"expansion_state":0,"options":{"engine":"r","label":"unnamed-chunk-71"},"document_id":"3D37876B","chunk_id":"cdhihoqrirn2r","chunk_label":"unnamed-chunk-6"},{"row":193,"row_count":1,"visible":true,"expansion_state":0,"options":{"engine":"r","label":"unnamed-chunk-72"},"document_id":"3D37876B","chunk_id":"cu0gyi4avw814","chunk_label":"unnamed-chunk-7"},{"row":203,"row_count":1,"visible":true,"expansion_state":0,"options":{"engine":"r","label":"unnamed-chunk-92"},"document_id":"3D37876B","chunk_id":"cduo9ky0kz14j","chunk_label":"unnamed-chunk-8"},{"row":213,"row_count":1,"visible":true,"expansion_state":0,"options":{"engine":"r","label":"unnamed-chunk-74"},"document_id":"3D37876B","chunk_id":"cphn6wbh5dj34","chunk_label":"unnamed-chunk-9"},{"row":221,"row_count":1,"visible":true,"expansion_state":0,"options":{"engine":"r","label":"unnamed-chunk-75"},"document_id":"3D37876B","chunk_id":"cpq6ngvja7wsb","chunk_label":"unnamed-chunk-10"},{"row":232,"row_count":1,"visible":true,"expansion_state":0,"options":{"engine":"r","label":"unnamed-chunk-76"},"document_id":"3D37876B","chunk_id":"c36o3ybbbtbfq","chunk_label":"tbl-LABEL3"},{"row":239,"row_count":1,"visible":true,"expansion_state":0,"options":{"engine":"r","label":"unnamed-chunk-77"},"document_id":"3D37876B","chunk_id":"cmsj5cy2p4l9n","chunk_label":"tbl-LABEL4"},{"row":246,"row_count":1,"visible":true,"expansion_state":0,"options":{"engine":"r","label":"unnamed-chunk-1"},"document_id":"3D37876B","chunk_id":"cz6rzlo5nxszk","chunk_label":"tbl-LABEL5"},{"row":255,"row_count":1,"visible":true,"expansion_state":0,"options":{"engine":"r","label":"unnamed-chunk-2"},"document_id":"3D37876B","chunk_id":"cpxo47euhprst","chunk_label":"unnamed-chunk-11"},{"row":263,"row_count":1,"visible":true,"expansion_state":0,"options":{"engine":"r","label":"unnamed-chunk-3"},"document_id":"3D37876B","chunk_id":"csgc3mb45yyto","chunk_label":"unnamed-chunk-12"},{"row":271,"row_count":1,"visible":true,"expansion_state":0,"options":{"engine":"r","label":"unnamed-chunk-4"},"document_id":"3D37876B","chunk_id":"cfa63tkslan8z","chunk_label":"unnamed-chunk-13"},{"row":277,"row_count":1,"visible":true,"expansion_state":0,"options":{"engine":"r","label":"unnamed-chunk-5"},"document_id":"3D37876B","chunk_id":"cyax1ahr6lk9w","chunk_label":"unnamed-chunk-14"},{"row":290,"row_count":1,"visible":true,"expansion_state":0,"options":{"engine":"r","label":"unnamed-chunk-6"},"document_id":"3D37876B","chunk_id":"c6eelsb0h91ko","chunk_label":"unnamed-chunk-15"},{"row":305,"row_count":1,"visible":true,"expansion_state":0,"options":{"engine":"r","label":"unnamed-chunk-7"},"document_id":"3D37876B","chunk_id":"cqican9kgmh0z","chunk_label":"unnamed-chunk-16"},{"row":313,"row_count":1,"visible":true,"expansion_state":0,"options":{"engine":"r","label":"unnamed-chunk-86"},"document_id":"3D37876B","chunk_id":"c5teze7wzfsc5","chunk_label":"unnamed-chunk-17"},{"row":323,"row_count":1,"visible":true,"expansion_state":0,"options":{"engine":"r","label":"unnamed-chunk-87"},"document_id":"3D37876B","chunk_id":"cp9ulwt5cn5d9","chunk_label":"unnamed-chunk-18"},{"row":331,"row_count":1,"visible":true,"expansion_state":0,"options":{"engine":"r","label":"unnamed-chunk-88"},"document_id":"3D37876B","chunk_id":"c9bi4ff0tnlrz","chunk_label":"unnamed-chunk-19"},{"row":339,"row_count":1,"visible":true,"expansion_state":0,"options":{"engine":"r","label":"unnamed-chunk-89"},"document_id":"3D37876B","chunk_id":"ceqzpg9zjq1us","chunk_label":"unnamed-chunk-20"},{"row":345,"row_count":1,"visible":true,"expansion_state":0,"options":{"engine":"r","label":"unnamed-chunk-90"},"document_id":"3D37876B","chunk_id":"cwu9xa7zyqe0f","chunk_label":"unnamed-chunk-21"}],"doc_write_time":1696542838,"chunk_rendered_width":700}